{
	"class" : {
		"appName" : "TommasoDalSasso 1/14/2016 23:45",
		"enabled" : "TommasoDalSasso 1/15/2016 00:10",
		"enabledComponents" : "TommasoDalSasso 2/10/2016 01:46",
		"initialize" : "TommasoDalSasso 1/20/2016 15:04",
		"isAbstract" : "TommasoDalSasso 1/20/2016 14:46",
		"register" : "TommasoDalSasso 2/10/2016 01:47",
		"unregister" : "TommasoDalSasso 1/14/2016 23:53",
		"url" : "TommasoDalSasso 1/26/2016 15:04" },
	"instance" : {
		"active" : "TommasoDalSasso 1/15/2016 10:53",
		"active:" : "TommasoDalSasso 1/15/2016 10:53",
		"children" : "TommasoDalSasso 1/19/2016 01:51",
		"defaultActive" : "TommasoDalSasso 1/15/2016 10:54",
		"includeLibs:" : "TommasoDalSasso 1/26/2016 16:42",
		"initialize" : "TommasoDalSasso 1/19/2016 01:45",
		"initializeChildren" : "TommasoDalSasso 1/15/2016 10:51",
		"renderActiveComponentOn:" : "TommasoDalSasso 1/15/2016 10:48",
		"renderContentOn:" : "TommasoDalSasso 1/18/2016 11:13",
		"showPage:" : "TommasoDalSasso 1/19/2016 02:14",
		"title" : "TommasoDalSasso 1/15/2016 11:44",
		"updateRoot:" : "TommasoDalSasso 1/26/2016 13:43" } }
